bahasa_nusantara/LICENSE
bahasa_nusantara/__init__.py
bahasa_nusantara/indo.py
bahasa_nusantara-2.0.0.dist-info/METADATA
bahasa_nusantara-2.0.0.dist-info/WHEEL
bahasa_nusantara-2.0.0.dist-info/entry_points.txt
bahasa_nusantara-2.0.0.dist-info/top_level.txt
bahasa_nusantara-2.0.0.dist-info/RECORD
