Metadata-Version: 2.4
Name: bahasa-nusantara
Version: 2.0.0
Summary: Python Interpreter dengan Sintaks Bahasa Indonesia untuk Pemula
Home-page: https://github.com/daffa-aditya-p/bahasa-nusantara
Author: Daffa Aditya Pratama
Author-email: Daffa Aditya Pratama <daffaadityp@proton.me>
Maintainer-email: Daffa Aditya Pratama <daffaadityp@proton.me>
License: MIT
Project-URL: Homepage, https://github.com/daffa-aditya-p/bahasa-nusantara
Project-URL: Repository, https://github.com/daffa-aditya-p/bahasa-nusantara
Project-URL: Bug Reports, https://github.com/daffa-aditya-p/bahasa-nusantara/issues
Project-URL: Documentation, https://github.com/daffa-aditya-p/bahasa-nusantara#readme
Keywords: indonesian,bahasa,indonesia,python,interpreter,programming,education,beginner,nusantara
Classifier: Development Status :: 4 - Beta
Classifier: Intended Audience :: Education
Classifier: Intended Audience :: Developers
Classifier: License :: OSI Approved :: MIT License
Classifier: Programming Language :: Python :: 3
Classifier: Programming Language :: Python :: 3.7
Classifier: Programming Language :: Python :: 3.8
Classifier: Programming Language :: Python :: 3.9
Classifier: Programming Language :: Python :: 3.10
Classifier: Programming Language :: Python :: 3.11
Classifier: Programming Language :: Python :: 3.12
Classifier: Topic :: Education
Classifier: Topic :: Software Development :: Interpreters
Classifier: Natural Language :: Indonesian
Classifier: Operating System :: OS Independent
Requires-Python: >=3.7
Requires-Dist: termcolor>=1.1.0
Provides-Extra: dev
Requires-Dist: pytest>=6.0; extra == "dev"
Requires-Dist: pytest-cov>=2.0; extra == "dev"
Requires-Dist: black>=21.0; extra == "dev"
Requires-Dist: flake8>=3.8; extra == "dev"
Requires-Dist: mypy>=0.800; extra == "dev"
Provides-Extra: test
Requires-Dist: pytest>=6.0; extra == "test"
Requires-Dist: pytest-cov>=2.0; extra == "test"
Dynamic: author
Dynamic: home-page
Dynamic: requires-python
